AUTHORS
LICENSE
MANIFEST.in
README.md
setup.py
doc/Makefile
doc/source/api.rst
doc/source/index.rst
doc/source/user.rst
doc/theme/README
doc/theme/flasky/layout.html
doc/theme/flasky/theme.conf
doc/theme/flasky/static/flasky.css_t
thrush/__init__.py
thrush/rrd.py
thrush.egg-info/PKG-INFO
thrush.egg-info/SOURCES.txt
thrush.egg-info/dependency_links.txt
thrush.egg-info/top_level.txt