Metadata-Version: 1.1
Name: thrush
Version: 0.2
Summary: Alternative OO wrapper for rrdtool
Home-page: http://dev.0xdeadbeef.ch/thrush.git
Author: Tobias Heinzen
Author-email: tobias.heinzen@0xdeadbeef.ch
License: BSD
Platform: UNKNOWN
Classifier: Development Status :: 3 - Alpha
Classifier: Intended Audience :: Developers
Classifier: Intended Audience :: System Administrators
Classifier: License :: OSI Approved :: BSD License
Classifier: Topic :: Database :: Front-Ends
Classifier: Topic :: Software Development :: Libraries :: Python Modules
